data/__init__.py
data/popular_20k.data
spacin/__init__.py
spacin/__main__.py
spacin/algorithm.py
spacin/loader.py
spacin/spacin.py
spacin/validator.py
spacin-0.1.0.dist-info/DESCRIPTION.rst
spacin-0.1.0.dist-info/METADATA
spacin-0.1.0.dist-info/RECORD
spacin-0.1.0.dist-info/WHEEL
spacin-0.1.0.dist-info/entry_points.txt
spacin-0.1.0.dist-info/metadata.json
spacin-0.1.0.dist-info/top_level.txt
