Metadata-Version: 2.0
Name: spacin
Version: 0.1.0
Summary: Spacin, puts space between!
Home-page: https://gitlab.com/mohammadsalek/spacin
Author: Mohammad Salek
License: MIT
Platform: UNKNOWN
